pyproteins/__init__.py
pyproteins/alignment/__init__.py
pyproteins/alignment/nw_custom.py
pyproteins/alignment/scoringFunctions.py
pyproteins/alignment/scoringMatrix.py
pyproteins/container/Core.py
pyproteins/container/__init__.py
pyproteins/container/customCollection.py
pyproteins/sequence/__init__.py
pyproteins/sequence/msa.py
pyproteins/sequence/peptide.py
pyproteins/sequence/psipred.py
pyproteins/utils/__init__.py
pyproteins/utils/make_json_serializable.py
pyproteins/utils/miscellaneous.py
pyproteins/utils/tsv.py
pyproteins/utils/unixCmd.py
pyproteins-2.1.1.dist-info/METADATA
pyproteins-2.1.1.dist-info/WHEEL
pyproteins-2.1.1.dist-info/licenses/LICENSE
pyproteins-2.1.1.dist-info/RECORD
