Metadata-Version: 2.3
Name: pyproteins
Version: 2.1.1
Summary: General purpose bionformatics library
Requires-Python: >=3.9
Requires-Dist: lxml>4.7.1
Requires-Dist: numpy>1.26.1
